{
  "user_information": {
    "username": "eltercero",
    "gravatar": "73e6ae598b7a61be53afdc77af8df37d",
    "level": 28,
    "title": "Turtles",
    "about": "",
    "website": null,
    "twitter": null,
    "topics_count": 0,
    "posts_count": 13,
    "creation_date": 1456910061,
    "vacation_date": null
  },
  "requested_information": [
    {
      "character": "寺",
      "meaning": "temple",
      "onyomi": "じ",
      "kunyomi": "てら",
      "important_reading": "kunyomi",
      "level": 15,
      "nanori": null,
      "user_specific": {
        "unlocked_date": 1472997694,
        "user_synonyms": null,
        "meaning_note": null,
        "reading_note": null,
        "srs": "burned",
        "srs_numeric": 9,
        "available_date": 5089619155,
        "burned": true,
        "burned_date": 1488286776,
        "reactivated_date": 0,
        "meaning_correct": 8,
        "meaning_incorrect": 0,
        "meaning_max_streak": 8,
        "meaning_current_streak": 8,
        "reading_correct": 8,
        "reading_incorrect": 0,
        "reading_max_streak": 8,
        "reading_current_streak": 8
      }
    },
    {
      "character": "飯",
      "meaning": "meal, food",
      "onyomi": "はん",
      "kunyomi": "めし",
      "important_reading": "onyomi",
      "level": 15,
      "nanori": null,
      "user_specific": {
        "unlocked_date": 1472997694,
        "user_synonyms": null,
        "meaning_note": null,
        "reading_note": null,
        "srs": "enlighten",
        "srs_numeric": 8,
        "available_date": 1502726400,
        "burned": false,
        "burned_date": 0,
        "reactivated_date": 0,
        "meaning_correct": 12,
        "meaning_incorrect": 2,
        "meaning_max_streak": 7,
        "meaning_current_streak": 3,
        "reading_correct": 12,
        "reading_incorrect": 0,
        "reading_max_streak": 12,
        "reading_current_streak": 12
      }
    },
    {
      "character": "農",
      "meaning": "farming, agriculture",
      "onyomi": "のう",
      "kunyomi": null,
      "important_reading": "onyomi",
      "level": 10,
      "nanori": null,
      "user_specific": {
        "unlocked_date": 1465377088,
        "user_synonyms": null,
        "meaning_note": null,
        "reading_note": null,
        "srs": "enlighten",
        "srs_numeric": 8,
        "available_date": 1494932400,
        "burned": false,
        "burned_date": 0,
        "reactivated_date": 0,
        "meaning_correct": 12,
        "meaning_incorrect": 2,
        "meaning_max_streak": 9,
        "meaning_current_streak": 3,
        "reading_correct": 12,
        "reading_incorrect": 1,
        "reading_max_streak": 11,
        "reading_current_streak": 11
      }
    },
    {
      "character": "鳴",
      "meaning": "chirp",
      "onyomi": "めい",
      "kunyomi": "な",
      "important_reading": "kunyomi",
      "level": 10,
      "nanori": null,
      "user_specific": {
        "unlocked_date": 1465047627,
        "user_synonyms": null,
        "meaning_note": null,
        "reading_note": null,
        "srs": "enlighten",
        "srs_numeric": 8,
        "available_date": 1495125000,
        "burned": false,
        "burned_date": 0,
        "reactivated_date": 0,
        "meaning_correct": 10,
        "meaning_incorrect": 1,
        "meaning_max_streak": 7,
        "meaning_current_streak": 3,
        "reading_correct": 10,
        "reading_incorrect": 0,
        "reading_max_streak": 10,
        "reading_current_streak": 10
      }
    },
    {
      "character": "集",
      "meaning": "collect, gather",
      "onyomi": "しゅう",
      "kunyomi": "あつ",
      "important_reading": "onyomi",
      "level": 10,
      "nanori": null,
      "user_specific": {
        "unlocked_date": 1465377089,
        "user_synonyms": null,
        "meaning_note": null,
        "reading_note": null,
        "srs": "burned",
        "srs_numeric": 9,
        "available_date": 5089619155,
        "burned": true,
        "burned_date": 1485368750,
        "reactivated_date": 0,
        "meaning_correct": 11,
        "meaning_incorrect": 0,
        "meaning_max_streak": 11,
        "meaning_current_streak": 11,
        "reading_correct": 11,
        "reading_incorrect": 1,
        "reading_max_streak": 6,
        "reading_current_streak": 5
      }
    },
    {
      "character": "習",
      "meaning": "learn",
      "onyomi": "しゅう",
      "kunyomi": "なら",
      "important_reading": "onyomi",
      "level": 10,
      "nanori": null,
      "user_specific": {
        "unlocked_date": 1465047627,
        "user_synonyms": null,
        "meaning_note": null,
        "reading_note": null,
        "srs": "enlighten",
        "srs_numeric": 8,
        "available_date": 1502632800,
        "burned": false,
        "burned_date": 0,
        "reactivated_date": 0,
        "meaning_correct": 24,
        "meaning_incorrect": 5,
        "meaning_max_streak": 7,
        "meaning_current_streak": 5,
        "reading_correct": 24,
        "reading_incorrect": 4,
        "reading_max_streak": 9,
        "reading_current_streak": 5
      }
    },
    {
      "character": "飛",
      "meaning": "fly",
      "onyomi": "ひ",
      "kunyomi": "と",
      "important_reading": "onyomi",
      "level": 20,
      "nanori": null,
      "user_specific": {
        "unlocked_date": 1480762857,
        "user_synonyms": null,
        "meaning_note": null,
        "reading_note": null,
        "srs": "enlighten",
        "srs_numeric": 8,
        "available_date": 1496053800,
        "burned": false,
        "burned_date": 0,
        "reactivated_date": 0,
        "meaning_correct": 7,
        "meaning_incorrect": 0,
        "meaning_max_streak": 7,
        "meaning_current_streak": 7,
        "reading_correct": 7,
        "reading_incorrect": 0,
        "reading_max_streak": 7,
        "reading_current_streak": 7
      }
    },
    {
      "character": "酒",
      "meaning": "alcohol",
      "onyomi": "しゅ",
      "kunyomi": "さけ, さか",
      "important_reading": "onyomi",
      "level": 10,
      "nanori": null,
      "user_specific": {
        "unlocked_date": 1465377108,
        "user_synonyms": null,
        "meaning_note": null,
        "reading_note": null,
        "srs": "burned",
        "srs_numeric": 9,
        "available_date": 1481734800,
        "burned": true,
        "burned_date": 1481739175,
        "reactivated_date": 1481652775,
        "meaning_correct": 13,
        "meaning_incorrect": 0,
        "meaning_max_streak": 13,
        "meaning_current_streak": 13,
        "reading_correct": 13,
        "reading_incorrect": 2,
        "reading_max_streak": 7,
        "reading_current_streak": 7
      }
    },
    {
      "character": "速",
      "meaning": "fast",
      "onyomi": "そく",
      "kunyomi": "はや",
      "important_reading": "onyomi",
      "level": 10,
      "nanori": null,
      "user_specific": {
        "unlocked_date": 1465401848,
        "user_synonyms": null,
        "meaning_note": null,
        "reading_note": null,
        "srs": "enlighten",
        "srs_numeric": 8,
        "available_date": 1495884600,
        "burned": false,
        "burned_date": 0,
        "reactivated_date": 0,
        "meaning_correct": 10,
        "meaning_incorrect": 0,
        "meaning_max_streak": 10,
        "meaning_current_streak": 10,
        "reading_correct": 10,
        "reading_incorrect": 1,
        "reading_max_streak": 7,
        "reading_current_streak": 3
      }
    },
    {
      "character": "尻",
      "meaning": "butt",
      "onyomi": null,
      "kunyomi": "しり",
      "important_reading": "kunyomi",
      "level": 20,
      "nanori": null,
      "user_specific": {
        "unlocked_date": 1480442863,
        "user_synonyms": null,
        "meaning_note": null,
        "reading_note": null,
        "srs": "enlighten",
        "srs_numeric": 8,
        "available_date": 1496399400,
        "burned": false,
        "burned_date": 0,
        "reactivated_date": 0,
        "meaning_correct": 8,
        "meaning_incorrect": 0,
        "meaning_max_streak": 8,
        "meaning_current_streak": 8,
        "reading_correct": 8,
        "reading_incorrect": 1,
        "reading_max_streak": 8,
        "reading_current_streak": 8
      }
    },
    {
      "character": "械",
      "meaning": "contraption",
      "onyomi": "かい",
      "kunyomi": "かせ",
      "important_reading": "onyomi",
      "level": 20,
      "nanori": null,
      "user_specific": {
        "unlocked_date": 1480442862,
        "user_synonyms": [
          "aparato",
          "artilugio"
        ],
        "meaning_note": null,
        "reading_note": null,
        "srs": "enlighten",
        "srs_numeric": 8,
        "available_date": 1495620000,
        "burned": false,
        "burned_date": 0,
        "reactivated_date": 0,
        "meaning_correct": 7,
        "meaning_incorrect": 0,
        "meaning_max_streak": 7,
        "meaning_current_streak": 7,
        "reading_correct": 7,
        "reading_incorrect": 0,
        "reading_max_streak": 7,
        "reading_current_streak": 7
      }
    },
    {
      "character": "築",
      "meaning": "construct, build",
      "onyomi": "ちく",
      "kunyomi": "きず",
      "important_reading": "onyomi",
      "level": 15,
      "nanori": null,
      "user_specific": {
        "unlocked_date": 1473312991,
        "user_synonyms": null,
        "meaning_note": null,
        "reading_note": null,
        "srs": "master",
        "srs_numeric": 7,
        "available_date": 1495008000,
        "burned": false,
        "burned_date": 0,
        "reactivated_date": 0,
        "meaning_correct": 17,
        "meaning_incorrect": 1,
        "meaning_max_streak": 11,
        "meaning_current_streak": 6,
        "reading_correct": 17,
        "reading_incorrect": 4,
        "reading_max_streak": 7,
        "reading_current_streak": 5
      }
    },
    {
      "character": "業",
      "meaning": "business",
      "onyomi": "ぎょう",
      "kunyomi": null,
      "important_reading": "onyomi",
      "level": 10,
      "nanori": null,
      "user_specific": {
        "unlocked_date": 1465047627,
        "user_synonyms": null,
        "meaning_note": null,
        "reading_note": null,
        "srs": "burned",
        "srs_numeric": 9,
        "available_date": 5089619155,
        "burned": true,
        "burned_date": 1485945803,
        "reactivated_date": 0,
        "meaning_correct": 11,
        "meaning_incorrect": 1,
        "meaning_max_streak": 6,
        "meaning_current_streak": 5,
        "reading_correct": 11,
        "reading_incorrect": 0,
        "reading_max_streak": 11,
        "reading_current_streak": 11
      }
    },
    {
      "character": "余",
      "meaning": "surplus, excess",
      "onyomi": "よ",
      "kunyomi": "あま",
      "important_reading": "onyomi",
      "level": 20,
      "nanori": null,
      "user_specific": {
        "unlocked_date": 1480442862,
        "user_synonyms": null,
        "meaning_note": null,
        "reading_note": null,
        "srs": "guru",
        "srs_numeric": 6,
        "available_date": 1493839800,
        "burned": false,
        "burned_date": 0,
        "reactivated_date": 0,
        "meaning_correct": 17,
        "meaning_incorrect": 4,
        "meaning_max_streak": 7,
        "meaning_current_streak": 5,
        "reading_correct": 17,
        "reading_incorrect": 2,
        "reading_max_streak": 14,
        "reading_current_streak": 3
      }
    },
    {
      "character": "院",
      "meaning": "institution",
      "onyomi": "いん",
      "kunyomi": null,
      "important_reading": "onyomi",
      "level": 10,
      "nanori": null,
      "user_specific": {
        "unlocked_date": 1465047627,
        "user_synonyms": null,
        "meaning_note": null,
        "reading_note": null,
        "srs": "master",
        "srs_numeric": 7,
        "available_date": 1495087200,
        "burned": false,
        "burned_date": 0,
        "reactivated_date": 0,
        "meaning_correct": 22,
        "meaning_incorrect": 6,
        "meaning_max_streak": 7,
        "meaning_current_streak": 2,
        "reading_correct": 22,
        "reading_incorrect": 0,
        "reading_max_streak": 22,
        "reading_current_streak": 22
      }
    },
    {
      "character": "飲",
      "meaning": "drink",
      "onyomi": "いん",
      "kunyomi": "の",
      "important_reading": "kunyomi",
      "level": 10,
      "nanori": null,
      "user_specific": {
        "unlocked_date": 1465047627,
        "user_synonyms": null,
        "meaning_note": null,
        "reading_note": null,
        "srs": "burned",
        "srs_numeric": 9,
        "available_date": 5089619155,
        "burned": true,
        "burned_date": 1484934403,
        "reactivated_date": 0,
        "meaning_correct": 11,
        "meaning_incorrect": 1,
        "meaning_max_streak": 6,
        "meaning_current_streak": 5,
        "reading_correct": 11,
        "reading_incorrect": 0,
        "reading_max_streak": 11,
        "reading_current_streak": 11
      }
    },
    {
      "character": "顔",
      "meaning": "face",
      "onyomi": "がん",
      "kunyomi": "かお",
      "important_reading": "kunyomi",
      "level": 10,
      "nanori": null,
      "user_specific": {
        "unlocked_date": 1465377128,
        "user_synonyms": null,
        "meaning_note": null,
        "reading_note": null,
        "srs": "enlighten",
        "srs_numeric": 8,
        "available_date": 1494846000,
        "burned": false,
        "burned_date": 0,
        "reactivated_date": 0,
        "meaning_correct": 11,
        "meaning_incorrect": 2,
        "meaning_max_streak": 8,
        "meaning_current_streak": 3,
        "reading_correct": 11,
        "reading_incorrect": 1,
        "reading_max_streak": 11,
        "reading_current_streak": 11
      }
    },
    {
      "character": "聞",
      "meaning": "hear",
      "onyomi": "ぶん, もん",
      "kunyomi": "き",
      "important_reading": "onyomi",
      "level": 10,
      "nanori": null,
      "user_specific": {
        "unlocked_date": 1465047627,
        "user_synonyms": null,
        "meaning_note": null,
        "reading_note": null,
        "srs": "burned",
        "srs_numeric": 9,
        "available_date": 5090005800,
        "burned": true,
        "burned_date": 1490006617,
        "reactivated_date": 0,
        "meaning_correct": 16,
        "meaning_incorrect": 1,
        "meaning_max_streak": 11,
        "meaning_current_streak": 5,
        "reading_correct": 16,
        "reading_incorrect": 2,
        "reading_max_streak": 8,
        "reading_current_streak": 8
      }
    },
    {
      "character": "最",
      "meaning": "most",
      "onyomi": "さい",
      "kunyomi": "もっと",
      "important_reading": "onyomi",
      "level": 10,
      "nanori": null,
      "user_specific": {
        "unlocked_date": 1465047627,
        "user_synonyms": null,
        "meaning_note": null,
        "reading_note": null,
        "srs": "burned",
        "srs_numeric": 9,
        "available_date": 5089619155,
        "burned": true,
        "burned_date": 1485157235,
        "reactivated_date": 0,
        "meaning_correct": 15,
        "meaning_incorrect": 2,
        "meaning_max_streak": 10,
        "meaning_current_streak": 5,
        "reading_correct": 15,
        "reading_incorrect": 3,
        "reading_max_streak": 10,
        "reading_current_streak": 10
      }
    },
    {
      "character": "転",
      "meaning": "revolve",
      "onyomi": "てん",
      "kunyomi": "ころ",
      "important_reading": "onyomi",
      "level": 10,
      "nanori": null,
      "user_specific": {
        "unlocked_date": 1465047627,
        "user_synonyms": null,
        "meaning_note": null,
        "reading_note": null,
        "srs": "burned",
        "srs_numeric": 9,
        "available_date": 1481362200,
        "burned": true,
        "burned_date": 1481366609,
        "reactivated_date": 1481280209,
        "meaning_correct": 8,
        "meaning_incorrect": 0,
        "meaning_max_streak": 8,
        "meaning_current_streak": 8,
        "reading_correct": 8,
        "reading_incorrect": 0,
        "reading_max_streak": 8,
        "reading_current_streak": 8
      }
    },
    {
      "character": "鉄",
      "meaning": "iron",
      "onyomi": "てつ",
      "kunyomi": null,
      "important_reading": "onyomi",
      "level": 10,
      "nanori": null,
      "user_specific": {
        "unlocked_date": 1465377083,
        "user_synonyms": null,
        "meaning_note": null,
        "reading_note": null,
        "srs": "burned",
        "srs_numeric": 9,
        "available_date": 1481119200,
        "burned": true,
        "burned_date": 1481123601,
        "reactivated_date": 1481037201,
        "meaning_correct": 8,
        "meaning_incorrect": 0,
        "meaning_max_streak": 8,
        "meaning_current_streak": 8,
        "reading_correct": 8,
        "reading_incorrect": 0,
        "reading_max_streak": 8,
        "reading_current_streak": 8
      }
    },
    {
      "character": "機",
      "meaning": "machine",
      "onyomi": "き",
      "kunyomi": "はた",
      "important_reading": "onyomi",
      "level": 20,
      "nanori": null,
      "user_specific": {
        "unlocked_date": 1480442862,
        "user_synonyms": null,
        "meaning_note": null,
        "reading_note": null,
        "srs": "enlighten",
        "srs_numeric": 8,
        "available_date": 1495967400,
        "burned": false,
        "burned_date": 0,
        "reactivated_date": 0,
        "meaning_correct": 8,
        "meaning_incorrect": 0,
        "meaning_max_streak": 8,
        "meaning_current_streak": 8,
        "reading_correct": 8,
        "reading_incorrect": 1,
        "reading_max_streak": 8,
        "reading_current_streak": 8
      }
    },
    {
      "character": "運",
      "meaning": "carry, luck",
      "onyomi": "うん",
      "kunyomi": "はこ",
      "important_reading": "onyomi",
      "level": 10,
      "nanori": null,
      "user_specific": {
        "unlocked_date": 1465047627,
        "user_synonyms": null,
        "meaning_note": null,
        "reading_note": null,
        "srs": "enlighten",
        "srs_numeric": 8,
        "available_date": 1496939400,
        "burned": false,
        "burned_date": 0,
        "reactivated_date": 0,
        "meaning_correct": 17,
        "meaning_incorrect": 2,
        "meaning_max_streak": 12,
        "meaning_current_streak": 12,
        "reading_correct": 17,
        "reading_incorrect": 5,
        "reading_max_streak": 10,
        "reading_current_streak": 5
      }
    },
    {
      "character": "秋",
      "meaning": "autumn, fall",
      "onyomi": "None",
      "kunyomi": "あき",
      "important_reading": "kunyomi",
      "level": 15,
      "nanori": null,
      "user_specific": {
        "unlocked_date": 1472997694,
        "user_synonyms": null,
        "meaning_note": null,
        "reading_note": null,
        "srs": "burned",
        "srs_numeric": 9,
        "available_date": 5089619155,
        "burned": true,
        "burned_date": 1488196022,
        "reactivated_date": 0,
        "meaning_correct": 8,
        "meaning_incorrect": 0,
        "meaning_max_streak": 8,
        "meaning_current_streak": 8,
        "reading_correct": 8,
        "reading_incorrect": 0,
        "reading_max_streak": 8,
        "reading_current_streak": 8
      }
    },
    {
      "character": "経",
      "meaning": "passage of time, pass through, manage",
      "onyomi": "けい",
      "kunyomi": "た, へ",
      "important_reading": "onyomi",
      "level": 20,
      "nanori": null,
      "user_specific": {
        "unlocked_date": 1480442862,
        "user_synonyms": null,
        "meaning_note": null,
        "reading_note": null,
        "srs": "enlighten",
        "srs_numeric": 8,
        "available_date": 1496147400,
        "burned": false,
        "burned_date": 0,
        "reactivated_date": 0,
        "meaning_correct": 7,
        "meaning_incorrect": 0,
        "meaning_max_streak": 7,
        "meaning_current_streak": 7,
        "reading_correct": 7,
        "reading_incorrect": 0,
        "reading_max_streak": 7,
        "reading_current_streak": 7
      }
    },
    {
      "character": "岩",
      "meaning": "boulder",
      "onyomi": "がん",
      "kunyomi": "いわ",
      "important_reading": "kunyomi",
      "level": 15,
      "nanori": null,
      "user_specific": {
        "unlocked_date": 1472997694,
        "user_synonyms": null,
        "meaning_note": null,
        "reading_note": null,
        "srs": "burned",
        "srs_numeric": 9,
        "available_date": 5089619155,
        "burned": true,
        "burned_date": 1488739966,
        "reactivated_date": 0,
        "meaning_correct": 8,
        "meaning_incorrect": 0,
        "meaning_max_streak": 8,
        "meaning_current_streak": 8,
        "reading_correct": 8,
        "reading_incorrect": 0,
        "reading_max_streak": 8,
        "reading_current_streak": 8
      }
    },
    {
      "character": "帰",
      "meaning": "return, return home",
      "onyomi": "き",
      "kunyomi": "かえ",
      "important_reading": "kunyomi",
      "level": 15,
      "nanori": null,
      "user_specific": {
        "unlocked_date": 1472997694,
        "user_synonyms": null,
        "meaning_note": null,
        "reading_note": null,
        "srs": "burned",
        "srs_numeric": 9,
        "available_date": 5089619155,
        "burned": true,
        "burned_date": 1488440907,
        "reactivated_date": 0,
        "meaning_correct": 8,
        "meaning_incorrect": 0,
        "meaning_max_streak": 8,
        "meaning_current_streak": 8,
        "reading_correct": 8,
        "reading_incorrect": 0,
        "reading_max_streak": 8,
        "reading_current_streak": 8
      }
    },
    {
      "character": "昼",
      "meaning": "noon",
      "onyomi": "None",
      "kunyomi": "ひる",
      "important_reading": "kunyomi",
      "level": 15,
      "nanori": null,
      "user_specific": {
        "unlocked_date": 1472997694,
        "user_synonyms": null,
        "meaning_note": null,
        "reading_note": null,
        "srs": "enlighten",
        "srs_numeric": 8,
        "available_date": 1502872200,
        "burned": false,
        "burned_date": 0,
        "reactivated_date": 0,
        "meaning_correct": 16,
        "meaning_incorrect": 2,
        "meaning_max_streak": 12,
        "meaning_current_streak": 3,
        "reading_correct": 16,
        "reading_incorrect": 4,
        "reading_max_streak": 9,
        "reading_current_streak": 9
      }
    },
    {
      "character": "葉",
      "meaning": "leaf, leaves",
      "onyomi": "よう",
      "kunyomi": "は, ば",
      "important_reading": "kunyomi",
      "level": 10,
      "nanori": null,
      "user_specific": {
        "unlocked_date": 1465047627,
        "user_synonyms": null,
        "meaning_note": null,
        "reading_note": null,
        "srs": "burned",
        "srs_numeric": 9,
        "available_date": 1480329000,
        "burned": true,
        "burned_date": 1480333858,
        "reactivated_date": 1480247458,
        "meaning_correct": 10,
        "meaning_incorrect": 1,
        "meaning_max_streak": 10,
        "meaning_current_streak": 10,
        "reading_correct": 10,
        "reading_incorrect": 1,
        "reading_max_streak": 9,
        "reading_current_streak": 9
      }
    },
    {
      "character": "漢",
      "meaning": "chinese, china",
      "onyomi": "かん",
      "kunyomi": null,
      "important_reading": "onyomi",
      "level": 10,
      "nanori": null,
      "user_specific": {
        "unlocked_date": 1465377107,
        "user_synonyms": null,
        "meaning_note": null,
        "reading_note": null,
        "srs": "burned",
        "srs_numeric": 9,
        "available_date": 1480570200,
        "burned": true,
        "burned_date": 1480575043,
        "reactivated_date": 1480488643,
        "meaning_correct": 8,
        "meaning_incorrect": 0,
        "meaning_max_streak": 8,
        "meaning_current_streak": 8,
        "reading_correct": 8,
        "reading_incorrect": 0,
        "reading_max_streak": 8,
        "reading_current_streak": 8
      }
    },
    {
      "character": "坂",
      "meaning": "slope",
      "onyomi": "はん",
      "kunyomi": "さか",
      "important_reading": "kunyomi",
      "level": 15,
      "nanori": null,
      "user_specific": {
        "unlocked_date": 1472997694,
        "user_synonyms": null,
        "meaning_note": null,
        "reading_note": null,
        "srs": "burned",
        "srs_numeric": 9,
        "available_date": 5089619155,
        "burned": true,
        "burned_date": 1488407083,
        "reactivated_date": 0,
        "meaning_correct": 8,
        "meaning_incorrect": 0,
        "meaning_max_streak": 8,
        "meaning_current_streak": 8,
        "reading_correct": 8,
        "reading_incorrect": 0,
        "reading_max_streak": 8,
        "reading_current_streak": 8
      }
    },
    {
      "character": "泣",
      "meaning": "cry",
      "onyomi": "きゅう",
      "kunyomi": "な",
      "important_reading": "kunyomi",
      "level": 15,
      "nanori": null,
      "user_specific": {
        "unlocked_date": 1472997694,
        "user_synonyms": null,
        "meaning_note": null,
        "reading_note": null,
        "srs": "enlighten",
        "srs_numeric": 8,
        "available_date": 1502699400,
        "burned": false,
        "burned_date": 0,
        "reactivated_date": 0,
        "meaning_correct": 11,
        "meaning_incorrect": 1,
        "meaning_max_streak": 8,
        "meaning_current_streak": 3,
        "reading_correct": 11,
        "reading_incorrect": 1,
        "reading_max_streak": 11,
        "reading_current_streak": 11
      }
    },
    {
      "character": "猫",
      "meaning": "cat",
      "onyomi": "None",
      "kunyomi": "ねこ",
      "important_reading": "kunyomi",
      "level": 15,
      "nanori": null,
      "user_specific": {
        "unlocked_date": 1472997694,
        "user_synonyms": null,
        "meaning_note": null,
        "reading_note": null,
        "srs": "burned",
        "srs_numeric": 9,
        "available_date": 5089619155,
        "burned": true,
        "burned_date": 1488286764,
        "reactivated_date": 0,
        "meaning_correct": 8,
        "meaning_incorrect": 0,
        "meaning_max_streak": 8,
        "meaning_current_streak": 8,
        "reading_correct": 8,
        "reading_incorrect": 0,
        "reading_max_streak": 8,
        "reading_current_streak": 8
      }
    },
    {
      "character": "軍",
      "meaning": "army",
      "onyomi": "ぐん",
      "kunyomi": "None",
      "important_reading": "onyomi",
      "level": 15,
      "nanori": null,
      "user_specific": {
        "unlocked_date": 1472997694,
        "user_synonyms": null,
        "meaning_note": null,
        "reading_note": null,
        "srs": "enlighten",
        "srs_numeric": 8,
        "available_date": 1502569800,
        "burned": false,
        "burned_date": 0,
        "reactivated_date": 0,
        "meaning_correct": 10,
        "meaning_incorrect": 1,
        "meaning_max_streak": 7,
        "meaning_current_streak": 3,
        "reading_correct": 10,
        "reading_incorrect": 0,
        "reading_max_streak": 10,
        "reading_current_streak": 10
      }
    },
    {
      "character": "英",
      "meaning": "england, english",
      "onyomi": "えい",
      "kunyomi": "None",
      "important_reading": "onyomi",
      "level": 15,
      "nanori": null,
      "user_specific": {
        "unlocked_date": 1472997694,
        "user_synonyms": null,
        "meaning_note": null,
        "reading_note": null,
        "srs": "enlighten",
        "srs_numeric": 8,
        "available_date": 1493287200,
        "burned": false,
        "burned_date": 0,
        "reactivated_date": 0,
        "meaning_correct": 10,
        "meaning_incorrect": 1,
        "meaning_max_streak": 6,
        "meaning_current_streak": 4,
        "reading_correct": 10,
        "reading_incorrect": 0,
        "reading_max_streak": 10,
        "reading_current_streak": 10
      }
    },
    {
      "character": "信",
      "meaning": "believe, trust",
      "onyomi": "しん",
      "kunyomi": "しん",
      "important_reading": "onyomi",
      "level": 15,
      "nanori": null,
      "user_specific": {
        "unlocked_date": 1472997694,
        "user_synonyms": null,
        "meaning_note": null,
        "reading_note": null,
        "srs": "enlighten",
        "srs_numeric": 8,
        "available_date": 1493046000,
        "burned": false,
        "burned_date": 0,
        "reactivated_date": 0,
        "meaning_correct": 12,
        "meaning_incorrect": 2,
        "meaning_max_streak": 7,
        "meaning_current_streak": 4,
        "reading_correct": 12,
        "reading_incorrect": 1,
        "reading_max_streak": 11,
        "reading_current_streak": 11
      }
    },
    {
      "character": "変",
      "meaning": "change, strange",
      "onyomi": "へん",
      "kunyomi": "か",
      "important_reading": "onyomi",
      "level": 15,
      "nanori": null,
      "user_specific": {
        "unlocked_date": 1472997694,
        "user_synonyms": null,
        "meaning_note": null,
        "reading_note": null,
        "srs": "enlighten",
        "srs_numeric": 8,
        "available_date": 1492795800,
        "burned": false,
        "burned_date": 0,
        "reactivated_date": 0,
        "meaning_correct": 10,
        "meaning_incorrect": 0,
        "meaning_max_streak": 10,
        "meaning_current_streak": 10,
        "reading_correct": 10,
        "reading_incorrect": 1,
        "reading_max_streak": 6,
        "reading_current_streak": 4
      }
    },
    {
      "character": "仏",
      "meaning": "buddha",
      "onyomi": "ぶつ",
      "kunyomi": "ほとけ",
      "important_reading": "onyomi",
      "level": 15,
      "nanori": null,
      "user_specific": {
        "unlocked_date": 1472997694,
        "user_synonyms": null,
        "meaning_note": null,
        "reading_note": null,
        "srs": "enlighten",
        "srs_numeric": 8,
        "available_date": 1493287200,
        "burned": false,
        "burned_date": 0,
        "reactivated_date": 0,
        "meaning_correct": 10,
        "meaning_incorrect": 1,
        "meaning_max_streak": 6,
        "meaning_current_streak": 4,
        "reading_correct": 10,
        "reading_incorrect": 0,
        "reading_max_streak": 10,
        "reading_current_streak": 10
      }
    },
    {
      "character": "式",
      "meaning": "ritual, ceremony, equation",
      "onyomi": "しき",
      "kunyomi": null,
      "important_reading": "onyomi",
      "level": 15,
      "nanori": null,
      "user_specific": {
        "unlocked_date": 1472997694,
        "user_synonyms": null,
        "meaning_note": null,
        "reading_note": null,
        "srs": "guru",
        "srs_numeric": 6,
        "available_date": 1493920800,
        "burned": false,
        "burned_date": 0,
        "reactivated_date": 0,
        "meaning_correct": 12,
        "meaning_incorrect": 1,
        "meaning_max_streak": 10,
        "meaning_current_streak": 2,
        "reading_correct": 12,
        "reading_incorrect": 2,
        "reading_max_streak": 8,
        "reading_current_streak": 4
      }
    },
    {
      "character": "法",
      "meaning": "method, law",
      "onyomi": "ほう",
      "kunyomi": "None",
      "important_reading": "onyomi",
      "level": 15,
      "nanori": null,
      "user_specific": {
        "unlocked_date": 1473312983,
        "user_synonyms": null,
        "meaning_note": null,
        "reading_note": null,
        "srs": "enlighten",
        "srs_numeric": 8,
        "available_date": 1500723000,
        "burned": false,
        "burned_date": 0,
        "reactivated_date": 0,
        "meaning_correct": 21,
        "meaning_incorrect": 5,
        "meaning_max_streak": 6,
        "meaning_current_streak": 6,
        "reading_correct": 21,
        "reading_incorrect": 1,
        "reading_max_streak": 14,
        "reading_current_streak": 7
      }
    },
    {
      "character": "毒",
      "meaning": "poison",
      "onyomi": "どく",
      "kunyomi": "None",
      "important_reading": "onyomi",
      "level": 15,
      "nanori": null,
      "user_specific": {
        "unlocked_date": 1472997694,
        "user_synonyms": null,
        "meaning_note": null,
        "reading_note": null,
        "srs": "burned",
        "srs_numeric": 9,
        "available_date": 5090720400,
        "burned": true,
        "burned_date": 1490721330,
        "reactivated_date": 0,
        "meaning_correct": 13,
        "meaning_incorrect": 2,
        "meaning_max_streak": 7,
        "meaning_current_streak": 7,
        "reading_correct": 13,
        "reading_incorrect": 0,
        "reading_max_streak": 13,
        "reading_current_streak": 13
      }
    },
    {
      "character": "晩",
      "meaning": "night, evening",
      "onyomi": "ばん",
      "kunyomi": null,
      "important_reading": "onyomi",
      "level": 15,
      "nanori": null,
      "user_specific": {
        "unlocked_date": 1472997694,
        "user_synonyms": null,
        "meaning_note": null,
        "reading_note": null,
        "srs": "guru",
        "srs_numeric": 6,
        "available_date": 1493109000,
        "burned": false,
        "burned_date": 0,
        "reactivated_date": 0,
        "meaning_correct": 16,
        "meaning_incorrect": 4,
        "meaning_max_streak": 7,
        "meaning_current_streak": 4,
        "reading_correct": 16,
        "reading_incorrect": 0,
        "reading_max_streak": 16,
        "reading_current_streak": 16
      }
    },
    {
      "character": "災",
      "meaning": "disaster",
      "onyomi": "さい",
      "kunyomi": "わざわ",
      "important_reading": "onyomi",
      "level": 20,
      "nanori": null,
      "user_specific": {
        "unlocked_date": 1480762860,
        "user_synonyms": null,
        "meaning_note": null,
        "reading_note": null,
        "srs": "enlighten",
        "srs_numeric": 8,
        "available_date": 1495967400,
        "burned": false,
        "burned_date": 0,
        "reactivated_date": 0,
        "meaning_correct": 7,
        "meaning_incorrect": 0,
        "meaning_max_streak": 7,
        "meaning_current_streak": 7,
        "reading_correct": 7,
        "reading_incorrect": 0,
        "reading_max_streak": 7,
        "reading_current_streak": 7
      }
    },
    {
      "character": "在",
      "meaning": "exist",
      "onyomi": "ざい",
      "kunyomi": "None",
      "important_reading": "onyomi",
      "level": 20,
      "nanori": null,
      "user_specific": {
        "unlocked_date": 1480442863,
        "user_synonyms": null,
        "meaning_note": null,
        "reading_note": null,
        "srs": "enlighten",
        "srs_numeric": 8,
        "available_date": 1495967400,
        "burned": false,
        "burned_date": 0,
        "reactivated_date": 0,
        "meaning_correct": 7,
        "meaning_incorrect": 0,
        "meaning_max_streak": 7,
        "meaning_current_streak": 7,
        "reading_correct": 7,
        "reading_incorrect": 0,
        "reading_max_streak": 7,
        "reading_current_streak": 7
      }
    },
    {
      "character": "嫌",
      "meaning": "dislike",
      "onyomi": "けん",
      "kunyomi": "いや, きら",
      "important_reading": "onyomi",
      "level": 20,
      "nanori": null,
      "user_specific": {
        "unlocked_date": 1480762869,
        "user_synonyms": null,
        "meaning_note": null,
        "reading_note": null,
        "srs": "enlighten",
        "srs_numeric": 8,
        "available_date": 1497175200,
        "burned": false,
        "burned_date": 0,
        "reactivated_date": 0,
        "meaning_correct": 9,
        "meaning_incorrect": 0,
        "meaning_max_streak": 9,
        "meaning_current_streak": 9,
        "reading_correct": 9,
        "reading_incorrect": 1,
        "reading_max_streak": 6,
        "reading_current_streak": 6
      }
    },
    {
      "character": "妻",
      "meaning": "wife",
      "onyomi": "さい",
      "kunyomi": "つま",
      "important_reading": "onyomi",
      "level": 20,
      "nanori": null,
      "user_specific": {
        "unlocked_date": 1480442862,
        "user_synonyms": null,
        "meaning_note": null,
        "reading_note": null,
        "srs": "enlighten",
        "srs_numeric": 8,
        "available_date": 1495708200,
        "burned": false,
        "burned_date": 0,
        "reactivated_date": 0,
        "meaning_correct": 7,
        "meaning_incorrect": 0,
        "meaning_max_streak": 7,
        "meaning_current_streak": 7,
        "reading_correct": 7,
        "reading_incorrect": 0,
        "reading_max_streak": 7,
        "reading_current_streak": 7
      }
    },
    {
      "character": "圧",
      "meaning": "pressure",
      "onyomi": "あつ",
      "kunyomi": "None",
      "important_reading": "onyomi",
      "level": 20,
      "nanori": null,
      "user_specific": {
        "unlocked_date": 1480442863,
        "user_synonyms": null,
        "meaning_note": null,
        "reading_note": null,
        "srs": "enlighten",
        "srs_numeric": 8,
        "available_date": 1495708200,
        "burned": false,
        "burned_date": 0,
        "reactivated_date": 0,
        "meaning_correct": 7,
        "meaning_incorrect": 0,
        "meaning_max_streak": 7,
        "meaning_current_streak": 7,
        "reading_correct": 7,
        "reading_incorrect": 0,
        "reading_max_streak": 7,
        "reading_current_streak": 7
      }
    },
    {
      "character": "倒",
      "meaning": "overthrow, collapse",
      "onyomi": "とう",
      "kunyomi": "たお",
      "important_reading": "onyomi",
      "level": 20,
      "nanori": null,
      "user_specific": {
        "unlocked_date": 1480762869,
        "user_synonyms": null,
        "meaning_note": null,
        "reading_note": null,
        "srs": "enlighten",
        "srs_numeric": 8,
        "available_date": 1500658200,
        "burned": false,
        "burned_date": 0,
        "reactivated_date": 0,
        "meaning_correct": 11,
        "meaning_incorrect": 1,
        "meaning_max_streak": 7,
        "meaning_current_streak": 4,
        "reading_correct": 11,
        "reading_incorrect": 1,
        "reading_max_streak": 11,
        "reading_current_streak": 11
      }
    },
    {
      "character": "裕",
      "meaning": "abundant, plentiful",
      "onyomi": "ゆう",
      "kunyomi": "None",
      "important_reading": "onyomi",
      "level": 20,
      "nanori": null,
      "user_specific": {
        "unlocked_date": 1480442862,
        "user_synonyms": null,
        "meaning_note": null,
        "reading_note": null,
        "srs": "enlighten",
        "srs_numeric": 8,
        "available_date": 1495884600,
        "burned": false,
        "burned_date": 0,
        "reactivated_date": 0,
        "meaning_correct": 7,
        "meaning_incorrect": 0,
        "meaning_max_streak": 7,
        "meaning_current_streak": 7,
        "reading_correct": 7,
        "reading_incorrect": 0,
        "reading_max_streak": 7,
        "reading_current_streak": 7
      }
    },
    {
      "character": "議",
      "meaning": "deliberation, discussion",
      "onyomi": "ぎ",
      "kunyomi": "None",
      "important_reading": "onyomi",
      "level": 20,
      "nanori": null,
      "user_specific": {
        "unlocked_date": 1480784440,
        "user_synonyms": null,
        "meaning_note": null,
        "reading_note": null,
        "srs": "enlighten",
        "srs_numeric": 8,
        "available_date": 1496993400,
        "burned": false,
        "burned_date": 0,
        "reactivated_date": 0,
        "meaning_correct": 10,
        "meaning_incorrect": 1,
        "meaning_max_streak": 7,
        "meaning_current_streak": 7,
        "reading_correct": 10,
        "reading_incorrect": 1,
        "reading_max_streak": 10,
        "reading_current_streak": 10
      }
    },
    {
      "character": "穴",
      "meaning": "hole, cave",
      "onyomi": "けつ",
      "kunyomi": "あな",
      "important_reading": "kunyomi",
      "level": 20,
      "nanori": null,
      "user_specific": {
        "unlocked_date": 1480442863,
        "user_synonyms": null,
        "meaning_note": null,
        "reading_note": null,
        "srs": "enlighten",
        "srs_numeric": 8,
        "available_date": 1495620000,
        "burned": false,
        "burned_date": 0,
        "reactivated_date": 0,
        "meaning_correct": 7,
        "meaning_incorrect": 0,
        "meaning_max_streak": 7,
        "meaning_current_streak": 7,
        "reading_correct": 7,
        "reading_incorrect": 0,
        "reading_max_streak": 7,
        "reading_current_streak": 7
      }
    },
    {
      "character": "害",
      "meaning": "damage, injury, harm",
      "onyomi": "がい",
      "kunyomi": "None",
      "important_reading": "onyomi",
      "level": 20,
      "nanori": null,
      "user_specific": {
        "unlocked_date": 1480442863,
        "user_synonyms": null,
        "meaning_note": null,
        "reading_note": null,
        "srs": "enlighten",
        "srs_numeric": 8,
        "available_date": 1502213400,
        "burned": false,
        "burned_date": 0,
        "reactivated_date": 0,
        "meaning_correct": 13,
        "meaning_incorrect": 1,
        "meaning_max_streak": 8,
        "meaning_current_streak": 8,
        "reading_correct": 13,
        "reading_incorrect": 1,
        "reading_max_streak": 9,
        "reading_current_streak": 4
      }
    },
    {
      "character": "論",
      "meaning": "theory",
      "onyomi": "ろん",
      "kunyomi": "None",
      "important_reading": "onyomi",
      "level": 20,
      "nanori": null,
      "user_specific": {
        "unlocked_date": 1480442862,
        "user_synonyms": null,
        "meaning_note": null,
        "reading_note": null,
        "srs": "enlighten",
        "srs_numeric": 8,
        "available_date": 1495810800,
        "burned": false,
        "burned_date": 0,
        "reactivated_date": 0,
        "meaning_correct": 7,
        "meaning_incorrect": 0,
        "meaning_max_streak": 7,
        "meaning_current_streak": 7,
        "reading_correct": 7,
        "reading_incorrect": 0,
        "reading_max_streak": 7,
        "reading_current_streak": 7
      }
    },
    {
      "character": "罪",
      "meaning": "guilt",
      "onyomi": "ざい",
      "kunyomi": "つみ",
      "important_reading": "onyomi",
      "level": 20,
      "nanori": null,
      "user_specific": {
        "unlocked_date": 1480442862,
        "user_synonyms": null,
        "meaning_note": null,
        "reading_note": null,
        "srs": "enlighten",
        "srs_numeric": 8,
        "available_date": 1500559200,
        "burned": false,
        "burned_date": 0,
        "reactivated_date": 0,
        "meaning_correct": 12,
        "meaning_incorrect": 1,
        "meaning_max_streak": 11,
        "meaning_current_streak": 11,
        "reading_correct": 12,
        "reading_incorrect": 1,
        "reading_max_streak": 8,
        "reading_current_streak": 4
      }
    },
    {
      "character": "難",
      "meaning": "difficult",
      "onyomi": "なん",
      "kunyomi": "むずか",
      "important_reading": "onyomi",
      "level": 20,
      "nanori": null,
      "user_specific": {
        "unlocked_date": 1480442862,
        "user_synonyms": null,
        "meaning_note": null,
        "reading_note": null,
        "srs": "enlighten",
        "srs_numeric": 8,
        "available_date": 1495967400,
        "burned": false,
        "burned_date": 0,
        "reactivated_date": 0,
        "meaning_correct": 8,
        "meaning_incorrect": 1,
        "meaning_max_streak": 8,
        "meaning_current_streak": 8,
        "reading_correct": 8,
        "reading_incorrect": 0,
        "reading_max_streak": 8,
        "reading_current_streak": 8
      }
    },
    {
      "character": "横",
      "meaning": "side",
      "onyomi": "おう",
      "kunyomi": "よこ",
      "important_reading": "kunyomi",
      "level": 10,
      "nanori": null,
      "user_specific": {
        "unlocked_date": 1465047627,
        "user_synonyms": null,
        "meaning_note": null,
        "reading_note": null,
        "srs": "guru",
        "srs_numeric": 6,
        "available_date": 1493395200,
        "burned": false,
        "burned_date": 0,
        "reactivated_date": 0,
        "meaning_correct": 23,
        "meaning_incorrect": 6,
        "meaning_max_streak": 7,
        "meaning_current_streak": 4,
        "reading_correct": 23,
        "reading_incorrect": 1,
        "reading_max_streak": 23,
        "reading_current_streak": 23
      }
    },
    {
      "character": "個",
      "meaning": "individual",
      "onyomi": "こ",
      "kunyomi": "None",
      "important_reading": "onyomi",
      "level": 20,
      "nanori": null,
      "user_specific": {
        "unlocked_date": 1480442863,
        "user_synonyms": null,
        "meaning_note": null,
        "reading_note": null,
        "srs": "enlighten",
        "srs_numeric": 8,
        "available_date": 1501065000,
        "burned": false,
        "burned_date": 0,
        "reactivated_date": 0,
        "meaning_correct": 10,
        "meaning_incorrect": 1,
        "meaning_max_streak": 6,
        "meaning_current_streak": 4,
        "reading_correct": 10,
        "reading_incorrect": 0,
        "reading_max_streak": 10,
        "reading_current_streak": 10
      }
    },
    {
      "character": "語",
      "meaning": "language",
      "onyomi": "ご",
      "kunyomi": "かた",
      "important_reading": "onyomi",
      "level": 10,
      "nanori": null,
      "user_specific": {
        "unlocked_date": 1465047627,
        "user_synonyms": null,
        "meaning_note": null,
        "reading_note": null,
        "srs": "burned",
        "srs_numeric": 9,
        "available_date": 1480507200,
        "burned": true,
        "burned_date": 1480512330,
        "reactivated_date": 1480425930,
        "meaning_correct": 8,
        "meaning_incorrect": 0,
        "meaning_max_streak": 8,
        "meaning_current_streak": 8,
        "reading_correct": 8,
        "reading_incorrect": 0,
        "reading_max_streak": 8,
        "reading_current_streak": 8
      }
    },
    {
      "character": "汁",
      "meaning": "soup",
      "onyomi": "じゅう",
      "kunyomi": "しる",
      "important_reading": "onyomi",
      "level": 35,
      "nanori": null,
      "user_specific": null
    },
    {
      "character": "厚",
      "meaning": "thick",
      "onyomi": "こう",
      "kunyomi": "あつ",
      "important_reading": "kunyomi",
      "level": 20,
      "nanori": null,
      "user_specific": {
        "unlocked_date": 1480442863,
        "user_synonyms": null,
        "meaning_note": null,
        "reading_note": null,
        "srs": "enlighten",
        "srs_numeric": 8,
        "available_date": 1498381200,
        "burned": false,
        "burned_date": 0,
        "reactivated_date": 0,
        "meaning_correct": 10,
        "meaning_incorrect": 1,
        "meaning_max_streak": 5,
        "meaning_current_streak": 5,
        "reading_correct": 10,
        "reading_incorrect": 0,
        "reading_max_streak": 10,
        "reading_current_streak": 10
      }
    },
    {
      "character": "単",
      "meaning": "simple",
      "onyomi": "たん",
      "kunyomi": "None",
      "important_reading": "onyomi",
      "level": 15,
      "nanori": null,
      "user_specific": {
        "unlocked_date": 1472997694,
        "user_synonyms": null,
        "meaning_note": null,
        "reading_note": null,
        "srs": "burned",
        "srs_numeric": 9,
        "available_date": 5092597800,
        "burned": true,
        "burned_date": 1492598030,
        "reactivated_date": 0,
        "meaning_correct": 11,
        "meaning_incorrect": 1,
        "meaning_max_streak": 6,
        "meaning_current_streak": 5,
        "reading_correct": 11,
        "reading_incorrect": 0,
        "reading_max_streak": 11,
        "reading_current_streak": 11
      }
    },
    {
      "character": "舎",
      "meaning": "cottage",
      "onyomi": "しゃ",
      "kunyomi": "None",
      "important_reading": "onyomi",
      "level": 35,
      "nanori": null,
      "user_specific": null
    },
    {
      "character": "滞",
      "meaning": "stagnate",
      "onyomi": "たい",
      "kunyomi": "とどこお",
      "important_reading": "onyomi",
      "level": 35,
      "nanori": null,
      "user_specific": null
    },
    {
      "character": "亀",
      "meaning": "turtle",
      "onyomi": "None",
      "kunyomi": "かめ",
      "important_reading": "kunyomi",
      "level": 35,
      "nanori": null,
      "user_specific": null
    },
    {
      "character": "介",
      "meaning": "jammed in",
      "onyomi": "かい",
      "kunyomi": null,
      "important_reading": "onyomi",
      "level": 35,
      "nanori": "すけ",
      "user_specific": null
    },
    {
      "character": "炎",
      "meaning": "flame, big fire",
      "onyomi": "えん",
      "kunyomi": "ほのお",
      "important_reading": "onyomi",
      "level": 35,
      "nanori": null,
      "user_specific": null
    },
    {
      "character": "厄",
      "meaning": "unlucky",
      "onyomi": "やく",
      "kunyomi": "None",
      "important_reading": "onyomi",
      "level": 35,
      "nanori": null,
      "user_specific": null
    },
    {
      "character": "講",
      "meaning": "lecture",
      "onyomi": "こう",
      "kunyomi": "None",
      "important_reading": "onyomi",
      "level": 35,
      "nanori": null,
      "user_specific": null
    },
    {
      "character": "互",
      "meaning": "mutual",
      "onyomi": "ご",
      "kunyomi": "たが",
      "important_reading": "onyomi",
      "level": 35,
      "nanori": null,
      "user_specific": null
    },
    {
      "character": "頭",
      "meaning": "head",
      "onyomi": "ず, とう",
      "kunyomi": "あたま",
      "important_reading": "kunyomi",
      "level": 10,
      "nanori": null,
      "user_specific": {
        "unlocked_date": 1465377128,
        "user_synonyms": null,
        "meaning_note": null,
        "reading_note": null,
        "srs": "enlighten",
        "srs_numeric": 8,
        "available_date": 1495531800,
        "burned": false,
        "burned_date": 0,
        "reactivated_date": 0,
        "meaning_correct": 10,
        "meaning_incorrect": 2,
        "meaning_max_streak": 7,
        "meaning_current_streak": 3,
        "reading_correct": 10,
        "reading_incorrect": 0,
        "reading_max_streak": 10,
        "reading_current_streak": 10
      }
    },
    {
      "character": "杉",
      "meaning": "cedar",
      "onyomi": "None",
      "kunyomi": "すぎ",
      "important_reading": "kunyomi",
      "level": 35,
      "nanori": null,
      "user_specific": null
    },
    {
      "character": "醤",
      "meaning": "soy sauce",
      "onyomi": "しょう",
      "kunyomi": "None",
      "important_reading": "onyomi",
      "level": 35,
      "nanori": null,
      "user_specific": null
    },
    {
      "character": "油",
      "meaning": "oil",
      "onyomi": "ゆ",
      "kunyomi": "あぶら",
      "important_reading": "onyomi",
      "level": 35,
      "nanori": null,
      "user_specific": null
    },
    {
      "character": "恥",
      "meaning": "shame",
      "onyomi": "ち",
      "kunyomi": "は, はじ",
      "important_reading": "kunyomi",
      "level": 35,
      "nanori": null,
      "user_specific": null
    },
    {
      "character": "彫",
      "meaning": "carve",
      "onyomi": "ちょう",
      "kunyomi": "ほ",
      "important_reading": "onyomi",
      "level": 35,
      "nanori": null,
      "user_specific": null
    },
    {
      "character": "算",
      "meaning": "calculate, calculation",
      "onyomi": "さん",
      "kunyomi": "そろ",
      "important_reading": "onyomi",
      "level": 10,
      "nanori": null,
      "user_specific": {
        "unlocked_date": 1465047627,
        "user_synonyms": null,
        "meaning_note": null,
        "reading_note": null,
        "srs": "burned",
        "srs_numeric": 9,
        "available_date": 5089619155,
        "burned": true,
        "burned_date": 1483695293,
        "reactivated_date": 0,
        "meaning_correct": 14,
        "meaning_incorrect": 2,
        "meaning_max_streak": 7,
        "meaning_current_streak": 7,
        "reading_correct": 14,
        "reading_incorrect": 0,
        "reading_max_streak": 14,
        "reading_current_streak": 14
      }
    },
    {
      "character": "歌",
      "meaning": "song, sing",
      "onyomi": "か",
      "kunyomi": "うた",
      "important_reading": "onyomi",
      "level": 10,
      "nanori": null,
      "user_specific": {
        "unlocked_date": 1465047627,
        "user_synonyms": null,
        "meaning_note": null,
        "reading_note": null,
        "srs": "burned",
        "srs_numeric": 9,
        "available_date": 1481205600,
        "burned": true,
        "burned_date": 1481209691,
        "reactivated_date": 1481123291,
        "meaning_correct": 9,
        "meaning_incorrect": 1,
        "meaning_max_streak": 9,
        "meaning_current_streak": 9,
        "reading_correct": 9,
        "reading_incorrect": 0,
        "reading_max_streak": 9,
        "reading_current_streak": 9
      }
    },
    {
      "character": "配",
      "meaning": "distribute",
      "onyomi": "はい",
      "kunyomi": "くば",
      "important_reading": "onyomi",
      "level": 10,
      "nanori": null,
      "user_specific": {
        "unlocked_date": 1465377108,
        "user_synonyms": null,
        "meaning_note": null,
        "reading_note": null,
        "srs": "burned",
        "srs_numeric": 9,
        "available_date": 1481362200,
        "burned": true,
        "burned_date": 1481366708,
        "reactivated_date": 1481280308,
        "meaning_correct": 8,
        "meaning_incorrect": 0,
        "meaning_max_streak": 8,
        "meaning_current_streak": 8,
        "reading_correct": 8,
        "reading_incorrect": 0,
        "reading_max_streak": 8,
        "reading_current_streak": 8
      }
    },
    {
      "character": "起",
      "meaning": "wake up",
      "onyomi": "き",
      "kunyomi": "お",
      "important_reading": "kunyomi",
      "level": 10,
      "nanori": null,
      "user_specific": {
        "unlocked_date": 1465047627,
        "user_synonyms": null,
        "meaning_note": null,
        "reading_note": null,
        "srs": "burned",
        "srs_numeric": 9,
        "available_date": 1481362200,
        "burned": true,
        "burned_date": 1481366723,
        "reactivated_date": 1481280323,
        "meaning_correct": 8,
        "meaning_incorrect": 0,
        "meaning_max_streak": 8,
        "meaning_current_streak": 8,
        "reading_correct": 8,
        "reading_incorrect": 0,
        "reading_max_streak": 8,
        "reading_current_streak": 8
      }
    },
    {
      "character": "確",
      "meaning": "certain",
      "onyomi": "かく",
      "kunyomi": "たし",
      "important_reading": "onyomi",
      "level": 20,
      "nanori": null,
      "user_specific": {
        "unlocked_date": 1480442862,
        "user_synonyms": null,
        "meaning_note": null,
        "reading_note": null,
        "srs": "enlighten",
        "srs_numeric": 8,
        "available_date": 1496527200,
        "burned": false,
        "burned_date": 0,
        "reactivated_date": 0,
        "meaning_correct": 9,
        "meaning_incorrect": 0,
        "meaning_max_streak": 9,
        "meaning_current_streak": 9,
        "reading_correct": 9,
        "reading_incorrect": 2,
        "reading_max_streak": 8,
        "reading_current_streak": 8
      }
    },
    {
      "character": "寿",
      "meaning": "lifespan",
      "onyomi": "じゅ, す",
      "kunyomi": "ことぶき",
      "important_reading": "onyomi",
      "level": 35,
      "nanori": null,
      "user_specific": null
    },
    {
      "character": "調",
      "meaning": "investigate, tone",
      "onyomi": "ちょう",
      "kunyomi": "しら",
      "important_reading": "onyomi",
      "level": 10,
      "nanori": null,
      "user_specific": {
        "unlocked_date": 1465047627,
        "user_synonyms": null,
        "meaning_note": null,
        "reading_note": null,
        "srs": "burned",
        "srs_numeric": 9,
        "available_date": 1481191200,
        "burned": true,
        "burned_date": 1481195716,
        "reactivated_date": 1481109316,
        "meaning_correct": 9,
        "meaning_incorrect": 1,
        "meaning_max_streak": 9,
        "meaning_current_streak": 9,
        "reading_correct": 9,
        "reading_incorrect": 0,
        "reading_max_streak": 9,
        "reading_current_streak": 9
      }
    },
    {
      "character": "線",
      "meaning": "line",
      "onyomi": "せん",
      "kunyomi": null,
      "important_reading": "onyomi",
      "level": 10,
      "nanori": null,
      "user_specific": {
        "unlocked_date": 1465047627,
        "user_synonyms": null,
        "meaning_note": null,
        "reading_note": null,
        "srs": "burned",
        "srs_numeric": 9,
        "available_date": 1481362200,
        "burned": true,
        "burned_date": 1481366686,
        "reactivated_date": 1481280286,
        "meaning_correct": 8,
        "meaning_incorrect": 0,
        "meaning_max_streak": 8,
        "meaning_current_streak": 8,
        "reading_correct": 8,
        "reading_incorrect": 0,
        "reading_max_streak": 8,
        "reading_current_streak": 8
      }
    },
    {
      "character": "防",
      "meaning": "prevent, prevention",
      "onyomi": "ぼう",
      "kunyomi": "ふせ",
      "important_reading": "onyomi",
      "level": 20,
      "nanori": null,
      "user_specific": {
        "unlocked_date": 1480442863,
        "user_synonyms": null,
        "meaning_note": null,
        "reading_note": null,
        "srs": "enlighten",
        "srs_numeric": 8,
        "available_date": 1498473000,
        "burned": false,
        "burned_date": 0,
        "reactivated_date": 0,
        "meaning_correct": 10,
        "meaning_incorrect": 1,
        "meaning_max_streak": 5,
        "meaning_current_streak": 5,
        "reading_correct": 10,
        "reading_incorrect": 1,
        "reading_max_streak": 5,
        "reading_current_streak": 5
      }
    },
    {
      "character": "犯",
      "meaning": "crime",
      "onyomi": "はん",
      "kunyomi": "おか",
      "important_reading": "onyomi",
      "level": 20,
      "nanori": null,
      "user_specific": {
        "unlocked_date": 1480442863,
        "user_synonyms": null,
        "meaning_note": null,
        "reading_note": null,
        "srs": "enlighten",
        "srs_numeric": 8,
        "available_date": 1496676600,
        "burned": false,
        "burned_date": 0,
        "reactivated_date": 0,
        "meaning_correct": 8,
        "meaning_incorrect": 0,
        "meaning_max_streak": 8,
        "meaning_current_streak": 8,
        "reading_correct": 8,
        "reading_incorrect": 1,
        "reading_max_streak": 8,
        "reading_current_streak": 8
      }
    },
    {
      "character": "晴",
      "meaning": "clear up",
      "onyomi": "せい",
      "kunyomi": "は",
      "important_reading": "kunyomi",
      "level": 15,
      "nanori": null,
      "user_specific": {
        "unlocked_date": 1472997694,
        "user_synonyms": null,
        "meaning_note": null,
        "reading_note": null,
        "srs": "master",
        "srs_numeric": 7,
        "available_date": 1494399600,
        "burned": false,
        "burned_date": 0,
        "reactivated_date": 0,
        "meaning_correct": 15,
        "meaning_incorrect": 2,
        "meaning_max_streak": 9,
        "meaning_current_streak": 5,
        "reading_correct": 15,
        "reading_incorrect": 2,
        "reading_max_streak": 8,
        "reading_current_streak": 7
      }
    },
    {
      "character": "噌",
      "meaning": "boisterous",
      "onyomi": "そ",
      "kunyomi": "None",
      "important_reading": "onyomi",
      "level": 35,
      "nanori": null,
      "user_specific": null
    },
    {
      "character": "臭",
      "meaning": "stinking, stinky, smelly",
      "onyomi": "しゅう",
      "kunyomi": "くさ",
      "important_reading": "kunyomi",
      "level": 20,
      "nanori": null,
      "user_specific": {
        "unlocked_date": 1480442863,
        "user_synonyms": null,
        "meaning_note": null,
        "reading_note": null,
        "srs": "enlighten",
        "srs_numeric": 8,
        "available_date": 1496399400,
        "burned": false,
        "burned_date": 0,
        "reactivated_date": 0,
        "meaning_correct": 8,
        "meaning_incorrect": 0,
        "meaning_max_streak": 8,
        "meaning_current_streak": 8,
        "reading_correct": 8,
        "reading_incorrect": 1,
        "reading_max_streak": 8,
        "reading_current_streak": 8
      }
    },
    {
      "character": "尾",
      "meaning": "tail",
      "onyomi": "び",
      "kunyomi": "お, ぽ",
      "important_reading": "onyomi",
      "level": 20,
      "nanori": null,
      "user_specific": {
        "unlocked_date": 1480442863,
        "user_synonyms": null,
        "meaning_note": null,
        "reading_note": null,
        "srs": "enlighten",
        "srs_numeric": 8,
        "available_date": 1496917800,
        "burned": false,
        "burned_date": 0,
        "reactivated_date": 0,
        "meaning_correct": 9,
        "meaning_incorrect": 1,
        "meaning_max_streak": 6,
        "meaning_current_streak": 6,
        "reading_correct": 9,
        "reading_incorrect": 0,
        "reading_max_streak": 9,
        "reading_current_streak": 9
      }
    },
    {
      "character": "為",
      "meaning": "sake",
      "onyomi": "い",
      "kunyomi": "ため, な, す",
      "important_reading": "onyomi",
      "level": 35,
      "nanori": null,
      "user_specific": null
    },
    {
      "character": "紀",
      "meaning": "account, narrative",
      "onyomi": "き",
      "kunyomi": "None",
      "important_reading": "onyomi",
      "level": 15,
      "nanori": null,
      "user_specific": {
        "unlocked_date": 1472997694,
        "user_synonyms": null,
        "meaning_note": null,
        "reading_note": null,
        "srs": "enlighten",
        "srs_numeric": 8,
        "available_date": 1499684400,
        "burned": false,
        "burned_date": 0,
        "reactivated_date": 0,
        "meaning_correct": 25,
        "meaning_incorrect": 7,
        "meaning_max_streak": 6,
        "meaning_current_streak": 4,
        "reading_correct": 25,
        "reading_incorrect": 1,
        "reading_max_streak": 19,
        "reading_current_streak": 19
      }
    },
    {
      "character": "病",
      "meaning": "sick, sickness, ill, illness",
      "onyomi": "びょう",
      "kunyomi": "や, やまい",
      "important_reading": "onyomi",
      "level": 10,
      "nanori": null,
      "user_specific": {
        "unlocked_date": 1465377118,
        "user_synonyms": null,
        "meaning_note": null,
        "reading_note": null,
        "srs": "burned",
        "srs_numeric": 9,
        "available_date": 1480759200,
        "burned": true,
        "burned_date": 1480763094,
        "reactivated_date": 1480676694,
        "meaning_correct": 11,
        "meaning_incorrect": 0,
        "meaning_max_streak": 11,
        "meaning_current_streak": 11,
        "reading_correct": 11,
        "reading_incorrect": 2,
        "reading_max_streak": 8,
        "reading_current_streak": 8
      }
    },
    {
      "character": "浅",
      "meaning": "shallow",
      "onyomi": "せん",
      "kunyomi": "あさ",
      "important_reading": "kunyomi",
      "level": 15,
      "nanori": null,
      "user_specific": {
        "unlocked_date": 1472997694,
        "user_synonyms": null,
        "meaning_note": null,
        "reading_note": null,
        "srs": "enlighten",
        "srs_numeric": 8,
        "available_date": 1497823200,
        "burned": false,
        "burned_date": 0,
        "reactivated_date": 0,
        "meaning_correct": 19,
        "meaning_incorrect": 4,
        "meaning_max_streak": 6,
        "meaning_current_streak": 6,
        "reading_correct": 19,
        "reading_incorrect": 0,
        "reading_max_streak": 19,
        "reading_current_streak": 19
      }
    },
    {
      "character": "終",
      "meaning": "end, finish",
      "onyomi": "しゅう",
      "kunyomi": "おわ, お",
      "important_reading": "onyomi",
      "level": 10,
      "nanori": null,
      "user_specific": {
        "unlocked_date": 1465047627,
        "user_synonyms": null,
        "meaning_note": null,
        "reading_note": null,
        "srs": "enlighten",
        "srs_numeric": 8,
        "available_date": 1498836600,
        "burned": false,
        "burned_date": 0,
        "reactivated_date": 0,
        "meaning_correct": 18,
        "meaning_incorrect": 2,
        "meaning_max_streak": 9,
        "meaning_current_streak": 5,
        "reading_correct": 18,
        "reading_incorrect": 2,
        "reading_max_streak": 9,
        "reading_current_streak": 8
      }
    },
    {
      "character": "遅",
      "meaning": "slow",
      "onyomi": "ち",
      "kunyomi": "おそ, おく",
      "important_reading": "onyomi",
      "level": 35,
      "nanori": null,
      "user_specific": null
    },
    {
      "character": "己",
      "meaning": "oneself",
      "onyomi": "こ, き",
      "kunyomi": "おのれ",
      "important_reading": "onyomi",
      "level": 35,
      "nanori": null,
      "user_specific": null
    },
    {
      "character": "獄",
      "meaning": "prison",
      "onyomi": "ごく",
      "kunyomi": "None",
      "important_reading": "onyomi",
      "level": 35,
      "nanori": null,
      "user_specific": null
    },
    {
      "character": "春",
      "meaning": "spring",
      "onyomi": "しゅん",
      "kunyomi": "はる",
      "important_reading": "kunyomi",
      "level": 15,
      "nanori": null,
      "user_specific": {
        "unlocked_date": 1472997694,
        "user_synonyms": null,
        "meaning_note": null,
        "reading_note": null,
        "srs": "burned",
        "srs_numeric": 9,
        "available_date": 5089619155,
        "burned": true,
        "burned_date": 1488361619,
        "reactivated_date": 0,
        "meaning_correct": 10,
        "meaning_incorrect": 0,
        "meaning_max_streak": 10,
        "meaning_current_streak": 10,
        "reading_correct": 10,
        "reading_incorrect": 2,
        "reading_max_streak": 9,
        "reading_current_streak": 9
      }
    },
    {
      "character": "夫",
      "meaning": "husband",
      "onyomi": "ふう, ふ",
      "kunyomi": "おっと",
      "important_reading": "onyomi",
      "level": 15,
      "nanori": null,
      "user_specific": {
        "unlocked_date": 1472997694,
        "user_synonyms": null,
        "meaning_note": null,
        "reading_note": null,
        "srs": "enlighten",
        "srs_numeric": 8,
        "available_date": 1497963600,
        "burned": false,
        "burned_date": 0,
        "reactivated_date": 0,
        "meaning_correct": 16,
        "meaning_incorrect": 2,
        "meaning_max_streak": 7,
        "meaning_current_streak": 4,
        "reading_correct": 16,
        "reading_incorrect": 2,
        "reading_max_streak": 9,
        "reading_current_streak": 9
      }
    },
    {
      "character": "読",
      "meaning": "read",
      "onyomi": "とう, どく",
      "kunyomi": "よ",
      "important_reading": "kunyomi",
      "level": 10,
      "nanori": null,
      "user_specific": {
        "unlocked_date": 1465377077,
        "user_synonyms": null,
        "meaning_note": null,
        "reading_note": null,
        "srs": "enlighten",
        "srs_numeric": 8,
        "available_date": 1495125000,
        "burned": false,
        "burned_date": 0,
        "reactivated_date": 0,
        "meaning_correct": 10,
        "meaning_incorrect": 1,
        "meaning_max_streak": 7,
        "meaning_current_streak": 3,
        "reading_correct": 10,
        "reading_incorrect": 0,
        "reading_max_streak": 10,
        "reading_current_streak": 10
      }
    },
    {
      "character": "計",
      "meaning": "measure, measurement",
      "onyomi": "けい",
      "kunyomi": "はか",
      "important_reading": "onyomi",
      "level": 15,
      "nanori": null,
      "user_specific": {
        "unlocked_date": 1472997694,
        "user_synonyms": null,
        "meaning_note": null,
        "reading_note": null,
        "srs": "burned",
        "srs_numeric": 9,
        "available_date": 5089619155,
        "burned": true,
        "burned_date": 1488711492,
        "reactivated_date": 0,
        "meaning_correct": 8,
        "meaning_incorrect": 0,
        "meaning_max_streak": 8,
        "meaning_current_streak": 8,
        "reading_correct": 8,
        "reading_incorrect": 0,
        "reading_max_streak": 8,
        "reading_current_streak": 8
      }
    },
    {
      "character": "落",
      "meaning": "fall",
      "onyomi": "らく",
      "kunyomi": "お",
      "important_reading": "onyomi",
      "level": 10,
      "nanori": null,
      "user_specific": {
        "unlocked_date": 1465401841,
        "user_synonyms": null,
        "meaning_note": null,
        "reading_note": null,
        "srs": "master",
        "srs_numeric": 7,
        "available_date": 1494399600,
        "burned": false,
        "burned_date": 0,
        "reactivated_date": 0,
        "meaning_correct": 28,
        "meaning_incorrect": 2,
        "meaning_max_streak": 17,
        "meaning_current_streak": 5,
        "reading_correct": 28,
        "reading_incorrect": 8,
        "reading_max_streak": 8,
        "reading_current_streak": 4
      }
    },
    {
      "character": "夢",
      "meaning": "dream",
      "onyomi": "む",
      "kunyomi": "ゆめ",
      "important_reading": "onyomi",
      "level": 20,
      "nanori": null,
      "user_specific": {
        "unlocked_date": 1480442863,
        "user_synonyms": null,
        "meaning_note": null,
        "reading_note": null,
        "srs": "enlighten",
        "srs_numeric": 8,
        "available_date": 1495731600,
        "burned": false,
        "burned_date": 0,
        "reactivated_date": 0,
        "meaning_correct": 8,
        "meaning_incorrect": 0,
        "meaning_max_streak": 8,
        "meaning_current_streak": 8,
        "reading_correct": 8,
        "reading_incorrect": 1,
        "reading_max_streak": 8,
        "reading_current_streak": 8
      }
    },
    {
      "character": "震",
      "meaning": "earthquake, quake, shake",
      "onyomi": "しん",
      "kunyomi": "ふる",
      "important_reading": "onyomi",
      "level": 20,
      "nanori": null,
      "user_specific": {
        "unlocked_date": 1480442862,
        "user_synonyms": null,
        "meaning_note": null,
        "reading_note": null,
        "srs": "enlighten",
        "srs_numeric": 8,
        "available_date": 1495620000,
        "burned": false,
        "burned_date": 0,
        "reactivated_date": 0,
        "meaning_correct": 7,
        "meaning_incorrect": 0,
        "meaning_max_streak": 7,
        "meaning_current_streak": 7,
        "reading_correct": 7,
        "reading_incorrect": 0,
        "reading_max_streak": 7,
        "reading_current_streak": 7
      }
    },
    {
      "character": "産",
      "meaning": "give birth, birth",
      "onyomi": "さん",
      "kunyomi": "う",
      "important_reading": "onyomi",
      "level": 20,
      "nanori": null,
      "user_specific": {
        "unlocked_date": 1480442863,
        "user_synonyms": null,
        "meaning_note": null,
        "reading_note": null,
        "srs": "enlighten",
        "srs_numeric": 8,
        "available_date": 1496349000,
        "burned": false,
        "burned_date": 0,
        "reactivated_date": 0,
        "meaning_correct": 7,
        "meaning_incorrect": 0,
        "meaning_max_streak": 7,
        "meaning_current_streak": 7,
        "reading_correct": 7,
        "reading_incorrect": 0,
        "reading_max_streak": 7,
        "reading_current_streak": 7
      }
    },
    {
      "character": "昨",
      "meaning": "previous, yesterday",
      "onyomi": "さく",
      "kunyomi": "None",
      "important_reading": "onyomi",
      "level": 15,
      "nanori": null,
      "user_specific": {
        "unlocked_date": 1472997694,
        "user_synonyms": null,
        "meaning_note": null,
        "reading_note": null,
        "srs": "enlighten",
        "srs_numeric": 8,
        "available_date": 1495382400,
        "burned": false,
        "burned_date": 0,
        "reactivated_date": 0,
        "meaning_correct": 16,
        "meaning_incorrect": 3,
        "meaning_max_streak": 6,
        "meaning_current_streak": 4,
        "reading_correct": 16,
        "reading_incorrect": 3,
        "reading_max_streak": 9,
        "reading_current_streak": 9
      }
    },
    {
      "character": "酢",
      "meaning": "vinegar",
      "onyomi": "None",
      "kunyomi": "す",
      "important_reading": "kunyomi",
      "level": 35,
      "nanori": null,
      "user_specific": null
    },
    {
      "character": "区",
      "meaning": "district, ward",
      "onyomi": "く",
      "kunyomi": "None",
      "important_reading": "onyomi",
      "level": 15,
      "nanori": null,
      "user_specific": {
        "unlocked_date": 1472997694,
        "user_synonyms": null,
        "meaning_note": null,
        "reading_note": null,
        "srs": "burned",
        "srs_numeric": 9,
        "available_date": 5089619155,
        "burned": true,
        "burned_date": 1488620608,
        "reactivated_date": 0,
        "meaning_correct": 9,
        "meaning_incorrect": 0,
        "meaning_max_streak": 9,
        "meaning_current_streak": 9,
        "reading_correct": 9,
        "reading_incorrect": 1,
        "reading_max_streak": 9,
        "reading_current_streak": 9
      }
    },
    {
      "character": "測",
      "meaning": "measure",
      "onyomi": "そく",
      "kunyomi": "はか",
      "important_reading": "onyomi",
      "level": 35,
      "nanori": null,
      "user_specific": null
    },
    {
      "character": "率",
      "meaning": "percent, percentage",
      "onyomi": "りつ, そつ",
      "kunyomi": "ひき",
      "important_reading": "onyomi",
      "level": 20,
      "nanori": null,
      "user_specific": {
        "unlocked_date": 1480762858,
        "user_synonyms": null,
        "meaning_note": null,
        "reading_note": null,
        "srs": "enlighten",
        "srs_numeric": 8,
        "available_date": 1496250000,
        "burned": false,
        "burned_date": 0,
        "reactivated_date": 0,
        "meaning_correct": 8,
        "meaning_incorrect": 0,
        "meaning_max_streak": 8,
        "meaning_current_streak": 8,
        "reading_correct": 8,
        "reading_incorrect": 1,
        "reading_max_streak": 8,
        "reading_current_streak": 8
      }
    },
    {
      "character": "列",
      "meaning": "row",
      "onyomi": "れつ, れ",
      "kunyomi": "None",
      "important_reading": "onyomi",
      "level": 15,
      "nanori": null,
      "user_specific": {
        "unlocked_date": 1472997694,
        "user_synonyms": null,
        "meaning_note": null,
        "reading_note": null,
        "srs": "master",
        "srs_numeric": 7,
        "available_date": 1495303200,
        "burned": false,
        "burned_date": 0,
        "reactivated_date": 0,
        "meaning_correct": 35,
        "meaning_incorrect": 11,
        "meaning_max_streak": 6,
        "meaning_current_streak": 4,
        "reading_correct": 35,
        "reading_incorrect": 3,
        "reading_max_streak": 18,
        "reading_current_streak": 18
      }
    },
    {
      "character": "勇",
      "meaning": "courage, bravery, valor, valour",
      "onyomi": "ゆう",
      "kunyomi": "いさ",
      "important_reading": "onyomi",
      "level": 15,
      "nanori": null,
      "user_specific": {
        "unlocked_date": 1473313035,
        "user_synonyms": null,
        "meaning_note": null,
        "reading_note": null,
        "srs": "enlighten",
        "srs_numeric": 8,
        "available_date": 1502728200,
        "burned": false,
        "burned_date": 0,
        "reactivated_date": 0,
        "meaning_correct": 11,
        "meaning_incorrect": 0,
        "meaning_max_streak": 11,
        "meaning_current_streak": 11,
        "reading_correct": 11,
        "reading_incorrect": 2,
        "reading_max_streak": 8,
        "reading_current_streak": 3
      }
    },
    {
      "character": "司",
      "meaning": "director",
      "onyomi": "し",
      "kunyomi": "つかさど",
      "important_reading": "onyomi",
      "level": 15,
      "nanori": null,
      "user_specific": {
        "unlocked_date": 1472997694,
        "user_synonyms": null,
        "meaning_note": null,
        "reading_note": null,
        "srs": "master",
        "srs_numeric": 7,
        "available_date": 1494577800,
        "burned": false,
        "burned_date": 0,
        "reactivated_date": 0,
        "meaning_correct": 15,
        "meaning_incorrect": 1,
        "meaning_max_streak": 15,
        "meaning_current_streak": 15,
        "reading_correct": 15,
        "reading_incorrect": 3,
        "reading_max_streak": 8,
        "reading_current_streak": 5
      }
    },
    {
      "character": "建",
      "meaning": "build",
      "onyomi": "けん",
      "kunyomi": "た",
      "important_reading": "onyomi",
      "level": 15,
      "nanori": null,
      "user_specific": {
        "unlocked_date": 1472997694,
        "user_synonyms": null,
        "meaning_note": null,
        "reading_note": null,
        "srs": "burned",
        "srs_numeric": 9,
        "available_date": 5089619155,
        "burned": true,
        "burned_date": 1488711551,
        "reactivated_date": 0,
        "meaning_correct": 8,
        "meaning_incorrect": 0,
        "meaning_max_streak": 8,
        "meaning_current_streak": 8,
        "reading_correct": 8,
        "reading_incorrect": 0,
        "reading_max_streak": 8,
        "reading_current_streak": 8
      }
    },
    {
      "character": "軽",
      "meaning": "lightweight, light, light weight",
      "onyomi": "けい",
      "kunyomi": "かる, かろ",
      "important_reading": "kunyomi",
      "level": 10,
      "nanori": null,
      "user_specific": {
        "unlocked_date": 1465625099,
        "user_synonyms": null,
        "meaning_note": null,
        "reading_note": null,
        "srs": "guru",
        "srs_numeric": 6,
        "available_date": 1492963200,
        "burned": false,
        "burned_date": 0,
        "reactivated_date": 0,
        "meaning_correct": 17,
        "meaning_incorrect": 2,
        "meaning_max_streak": 7,
        "meaning_current_streak": 4,
        "reading_correct": 17,
        "reading_incorrect": 2,
        "reading_max_streak": 9,
        "reading_current_streak": 3
      }
    },
    {
      "character": "酔",
      "meaning": "drunk",
      "onyomi": "すい",
      "kunyomi": "よ",
      "important_reading": "onyomi",
      "level": 35,
      "nanori": null,
      "user_specific": null
    },
    {
      "character": "熊",
      "meaning": "bear",
      "onyomi": "None",
      "kunyomi": "くま",
      "important_reading": "kunyomi",
      "level": 35,
      "nanori": null,
      "user_specific": null
    },
    {
      "character": "丈",
      "meaning": "height, ten feet",
      "onyomi": "じょう",
      "kunyomi": "たけ",
      "important_reading": "onyomi",
      "level": 15,
      "nanori": null,
      "user_specific": {
        "unlocked_date": 1473312989,
        "user_synonyms": null,
        "meaning_note": null,
        "reading_note": null,
        "srs": "master",
        "srs_numeric": 7,
        "available_date": 1494766800,
        "burned": false,
        "burned_date": 0,
        "reactivated_date": 0,
        "meaning_correct": 12,
        "meaning_incorrect": 0,
        "meaning_max_streak": 12,
        "meaning_current_streak": 12,
        "reading_correct": 12,
        "reading_incorrect": 2,
        "reading_max_streak": 7,
        "reading_current_streak": 4
      }
    },
    {
      "character": "払",
      "meaning": "pay",
      "onyomi": "None",
      "kunyomi": "はら",
      "important_reading": "kunyomi",
      "level": 35,
      "nanori": null,
      "user_specific": null
    },
    {
      "character": "紹",
      "meaning": "introduce",
      "onyomi": "しょう",
      "kunyomi": "None",
      "important_reading": "onyomi",
      "level": 35,
      "nanori": null,
      "user_specific": null
    },
    {
      "character": "進",
      "meaning": "advance",
      "onyomi": "しん",
      "kunyomi": "すす",
      "important_reading": "onyomi",
      "level": 10,
      "nanori": null,
      "user_specific": {
        "unlocked_date": 1465377089,
        "user_synonyms": null,
        "meaning_note": null,
        "reading_note": null,
        "srs": "burned",
        "srs_numeric": 9,
        "available_date": 5089619155,
        "burned": true,
        "burned_date": 1485626104,
        "reactivated_date": 0,
        "meaning_correct": 14,
        "meaning_incorrect": 1,
        "meaning_max_streak": 14,
        "meaning_current_streak": 14,
        "reading_correct": 14,
        "reading_incorrect": 2,
        "reading_max_streak": 6,
        "reading_current_streak": 5
      }
    },
    {
      "character": "剣",
      "meaning": "sword",
      "onyomi": "けん",
      "kunyomi": "つるぎ",
      "important_reading": "onyomi",
      "level": 35,
      "nanori": null,
      "user_specific": null
    },
    {
      "character": "銅",
      "meaning": "copper",
      "onyomi": "どう",
      "kunyomi": "あかがね",
      "important_reading": "onyomi",
      "level": 35,
      "nanori": null,
      "user_specific": null
    },
    {
      "character": "鍋",
      "meaning": "pot",
      "onyomi": "None",
      "kunyomi": "なべ",
      "important_reading": "kunyomi",
      "level": 35,
      "nanori": null,
      "user_specific": null
    },
    {
      "character": "湖",
      "meaning": "lake",
      "onyomi": "こ",
      "kunyomi": "みずうみ",
      "important_reading": "onyomi",
      "level": 35,
      "nanori": null,
      "user_specific": null
    },
    {
      "character": "被",
      "meaning": "incur",
      "onyomi": "ひ",
      "kunyomi": "かぶ",
      "important_reading": "onyomi",
      "level": 20,
      "nanori": null,
      "user_specific": {
        "unlocked_date": 1480442862,
        "user_synonyms": null,
        "meaning_note": null,
        "reading_note": null,
        "srs": "enlighten",
        "srs_numeric": 8,
        "available_date": 1496053800,
        "burned": false,
        "burned_date": 0,
        "reactivated_date": 0,
        "meaning_correct": 8,
        "meaning_incorrect": 0,
        "meaning_max_streak": 8,
        "meaning_current_streak": 8,
        "reading_correct": 8,
        "reading_incorrect": 1,
        "reading_max_streak": 8,
        "reading_current_streak": 8
      }
    },
    {
      "character": "彼",
      "meaning": "he",
      "onyomi": "ひ",
      "kunyomi": "かれ, かの",
      "important_reading": "kunyomi",
      "level": 35,
      "nanori": null,
      "user_specific": null
    },
    {
      "character": "破",
      "meaning": "tear",
      "onyomi": "は",
      "kunyomi": "やぶ",
      "important_reading": "onyomi",
      "level": 35,
      "nanori": null,
      "user_specific": null
    },
    {
      "character": "妨",
      "meaning": "obstruct, impede",
      "onyomi": "ぼう",
      "kunyomi": "さまた",
      "important_reading": "onyomi",
      "level": 20,
      "nanori": null,
      "user_specific": {
        "unlocked_date": 1480442863,
        "user_synonyms": null,
        "meaning_note": null,
        "reading_note": null,
        "srs": "enlighten",
        "srs_numeric": 8,
        "available_date": 1496122200,
        "burned": false,
        "burned_date": 0,
        "reactivated_date": 0,
        "meaning_correct": 9,
        "meaning_incorrect": 0,
        "meaning_max_streak": 9,
        "meaning_current_streak": 9,
        "reading_correct": 9,
        "reading_incorrect": 2,
        "reading_max_streak": 8,
        "reading_current_streak": 8
      }
    },
    {
      "character": "路",
      "meaning": "road",
      "onyomi": "ろ",
      "kunyomi": "じ, みち",
      "important_reading": "onyomi",
      "level": 10,
      "nanori": null,
      "user_specific": {
        "unlocked_date": 1465401841,
        "user_synonyms": null,
        "meaning_note": null,
        "reading_note": null,
        "srs": "burned",
        "srs_numeric": 9,
        "available_date": 5089619155,
        "burned": true,
        "burned_date": 1485963682,
        "reactivated_date": 0,
        "meaning_correct": 11,
        "meaning_incorrect": 1,
        "meaning_max_streak": 6,
        "meaning_current_streak": 5,
        "reading_correct": 11,
        "reading_incorrect": 1,
        "reading_max_streak": 6,
        "reading_current_streak": 5
      }
    },
    {
      "character": "親",
      "meaning": "parent",
      "onyomi": "しん",
      "kunyomi": "おや, した",
      "important_reading": "onyomi",
      "level": 10,
      "nanori": null,
      "user_specific": {
        "unlocked_date": 1465047627,
        "user_synonyms": null,
        "meaning_note": null,
        "reading_note": null,
        "srs": "burned",
        "srs_numeric": 9,
        "available_date": 1481099400,
        "burned": true,
        "burned_date": 1481104033,
        "reactivated_date": 1481017633,
        "meaning_correct": 8,
        "meaning_incorrect": 0,
        "meaning_max_streak": 8,
        "meaning_current_streak": 8,
        "reading_correct": 8,
        "reading_incorrect": 0,
        "reading_max_streak": 8,
        "reading_current_streak": 8
      }
    },
    {
      "character": "開",
      "meaning": "open, opened",
      "onyomi": "かい",
      "kunyomi": "あ, ひら",
      "important_reading": "onyomi",
      "level": 10,
      "nanori": null,
      "user_specific": {
        "unlocked_date": 1465047627,
        "user_synonyms": null,
        "meaning_note": null,
        "reading_note": null,
        "srs": "burned",
        "srs_numeric": 9,
        "available_date": 1480676400,
        "burned": true,
        "burned_date": 1480681390,
        "reactivated_date": 1480594990,
        "meaning_correct": 8,
        "meaning_incorrect": 0,
        "meaning_max_streak": 8,
        "meaning_current_streak": 8,
        "reading_correct": 8,
        "reading_incorrect": 0,
        "reading_max_streak": 8,
        "reading_current_streak": 8
      }
    }
  ]
}